__init__.py
scregistry.py
data/README.rst
scregistry-0.3.1.dist-info/LICENSE.txt
scregistry-0.3.1.dist-info/METADATA
scregistry-0.3.1.dist-info/WHEEL
scregistry-0.3.1.dist-info/top_level.txt
scregistry-0.3.1.dist-info/RECORD
