Metadata-Version: 2.1
Name: scregistry
Version: 0.3.1
Summary: API for accessing the Shared Cloud Registry (scregistry) specification for sharing data in and across clouds
Author-email: Johns Hopkins University Applied Physics Laboratory LLC <sandy.antunes@jhuapl.edu>
License: The MIT License (MIT)
Project-URL: Homepage, https://heliocloud.org
Project-URL: Documentation, https://heliocloud.org
Project-URL: Repository, https://gitlab.smce.nasa.gov
Keywords: cloud,registry,AWS
Classifier: Development Status :: 4 - Beta
Classifier: Topic :: Utilities
Classifier: License :: OSI Approved :: MIT License
Requires-Python: >=3.8
License-File: LICENSE.txt
Requires-Dist: boto3
Requires-Dist: pandas
Requires-Dist: requests
